scrub/__init__.py
scrub/__version__.py
scrub/scrub.py
scrub-0.1.2.dist-info/WHEEL
scrub-0.1.2.dist-info/METADATA
scrub-0.1.2.dist-info/RECORD
