Metadata-Version: 2.1
Name: scrub
Version: 0.1.2
Summary: Scrub sensitive fields for production and data that keeps changing for testing.
Home-page: https://github.com/jondot/scrub
License: MIT
Keywords: dict,data,nested,functional
Author: Dotan Nahum
Author-email: jondotan@gmail.com
Classifier: License :: OSI Approved :: MIT License
Classifier: Programming Language :: Python :: 2
Classifier: Programming Language :: Python :: 2.7
Classifier: Programming Language :: Python :: 3
Classifier: Programming Language :: Python :: 3.4
Classifier: Programming Language :: Python :: 3.5
Classifier: Programming Language :: Python :: 3.6
Classifier: Programming Language :: Python :: 3.7
Provides-Extra: lint
Requires-Dist: cytoolz (>=0.9.0,<0.10.0)
Requires-Dist: toolz (>=0.9.0,<0.10.0)
Project-URL: Documentation, https://github.com/jondot/scrub
Project-URL: Repository, https://github.com/jondot/scrub
